mcp_server_rabbitmq/__init__.py
mcp_server_rabbitmq/admin.py
mcp_server_rabbitmq/connection.py
mcp_server_rabbitmq/constant.py
mcp_server_rabbitmq/handlers.py
mcp_server_rabbitmq/server.py
mcp_server_rabbitmq-2.2.0.dist-info/METADATA
mcp_server_rabbitmq-2.2.0.dist-info/WHEEL
mcp_server_rabbitmq-2.2.0.dist-info/entry_points.txt
mcp_server_rabbitmq-2.2.0.dist-info/licenses/LICENSE
mcp_server_rabbitmq-2.2.0.dist-info/RECORD
