Metadata-Version: 2.4
Name: mcp-server-rabbitmq
Version: 2.2.0
Summary: A Model Context Protocol server providing access to RabbitMQ by LLMs
Project-URL: Homepage, https://github.com/kenliao94/mcp-server-rabbitmq
Project-URL: Source, https://github.com/kenliao94/mcp-server-rabbitmq
Author: Ken Liao
Maintainer-email: Ken Liao <kenliao94@gmail.com>
License: Apache-2.0
License-File: LICENSE
Keywords: automation,llm,mcp,rabbitmq
Classifier: Development Status :: 4 - Beta
Classifier: Intended Audience :: Developers
Classifier: License :: OSI Approved :: Apache Software License
Classifier: Programming Language :: Python :: 3
Classifier: Programming Language :: Python :: 3.10
Classifier: Programming Language :: Python :: 3.11
Classifier: Programming Language :: Python :: 3.12
Requires-Python: >=3.10
Requires-Dist: fastmcp>=2.7.1
Requires-Dist: loguru>=0.7.3
Requires-Dist: markdownify>=0.13.1
Requires-Dist: mcp>=1.6.0
Requires-Dist: pika>=1.3.2
Requires-Dist: protego>=0.3.1
Requires-Dist: pydantic>=2.0.0
Requires-Dist: readabilipy>=0.2.0
Requires-Dist: requests>=2.32.3
